plinky/__init__.py
plinky/__main__.py
plinky/__version__.py
plinky/cli.py
plinky/config.py
plinky/render.py
plinky/types.py
plinky-0.1.dist-info/entry_points.txt
plinky-0.1.dist-info/LICENSE
plinky-0.1.dist-info/WHEEL
plinky-0.1.dist-info/METADATA
plinky-0.1.dist-info/RECORD
